testtesttest000001/__init__.py
testtesttest000001/_dolphindbcpp.cpython-38-x86_64-linux-gnu.so
testtesttest000001/_dolphindbcpp.pyi
testtesttest000001/_hints.py
testtesttest000001/cep.py
testtesttest000001/database.py
testtesttest000001/io.py
testtesttest000001/logger.py
testtesttest000001/session.py
testtesttest000001/settings.py
testtesttest000001/table.py
testtesttest000001/typing.py
testtesttest000001/utils.py
testtesttest000001/vector.py
testtesttest000001.libs/libuuid-f64cda11.so.1.3.0
testtesttest000001-2.1.2.dist-info/LICENSE
testtesttest000001-2.1.2.dist-info/METADATA
testtesttest000001-2.1.2.dist-info/WHEEL
testtesttest000001-2.1.2.dist-info/top_level.txt
testtesttest000001-2.1.2.dist-info/RECORD
