Metadata-Version: 2.1
Name: testtesttest000001
Version: 2.1.2
Summary: A C++ boosted DolphinDB Python API based on Pybind11
Author-email: "DolphinDB, Inc." <support@dolphindb.com>
License: DolphinDB
Project-URL: Homepage, https://dolphindb.com
Classifier: Programming Language :: Python
Classifier: Programming Language :: Python :: 3
Classifier: Programming Language :: Python :: 3.8
Classifier: Programming Language :: Python :: 3.9
Classifier: Programming Language :: Python :: 3.10
Classifier: Programming Language :: Python :: 3.11
Classifier: Programming Language :: Python :: 3.12
Classifier: Programming Language :: Python :: 3.13
Classifier: Programming Language :: Python :: Implementation :: CPython
Classifier: Operating System :: POSIX :: Linux
Classifier: Operating System :: Microsoft :: Windows
Classifier: Operating System :: MacOS
Requires-Python: >=3.8
License-File: LICENSE
Requires-Dist: numpy>=1.18.0
Requires-Dist: pandas!=1.3.0,>=1.0.0
Requires-Dist: future
Requires-Dist: packaging
